tellovision/__init__.py
tellovision-0.0.1.dist-info/LICENSE
tellovision-0.0.1.dist-info/METADATA
tellovision-0.0.1.dist-info/WHEEL
tellovision-0.0.1.dist-info/top_level.txt
tellovision-0.0.1.dist-info/RECORD
